airobot_api_client/__about__.py
airobot_api_client/__init__.py
airobot_api_client/api.py
airobot_api_client/async_api.py
airobot_api_client/models.py
airobot_api_client/py.typed
airobot_api_client-0.4.1.dist-info/METADATA
airobot_api_client-0.4.1.dist-info/WHEEL
airobot_api_client-0.4.1.dist-info/licenses/LICENSE
airobot_api_client-0.4.1.dist-info/RECORD
